[
  {
    "blk": "ခွဲးဟဝ်ဒျာႏ",
    "translations": {
      "my": "မင်္ဂလာပါ",
      "en": "Hello",
      "ja": "こんにちは",
      "zh": "你好"
    }
  },
  {
    "blk": "အုံဟဝ်နေဟောင်း",
    "translations": {
      "my": "နေကောင်းလား",
      "en": "How are you?",
      "ja": "お元気ですか？",
      "zh": "你好吗？"
    }
  },
  {
    "blk": "ခွေသွဉ်း အုံဟဝ်ဒျာႏ",
    "translations": {
      "my": "ကျွန်တော် နေကောင်းပါတယ်",
      "en": "I am fine",
      "ja": "元気です",
      "zh": "我很好"
    }
  },
  {
    "blk": "နာꩻမဉ်ꩻတမုဲင်ꩻ",
    "translations": {
      "my": "မင်းနာမည် ဘယ်လိုခေါ်လဲ",
      "en": "What is your name?",
      "ja": "あなたの名前は何ですか？",
      "zh": "你叫什么名字？"
    }
  },
  {
    "blk": "ကေႏဇူꩻတင်ႏငါႏ",
    "translations": {
      "my": "ကျေးဇူးတင်ပါတယ်",
      "en": "Thank you",
      "ja": "ありがとうございます",
      "zh": "谢谢"
    }
  }
]
